okta_py_ma/__init__.py
okta_py_ma-0.0.2.dist-info/LICENSE
okta_py_ma-0.0.2.dist-info/METADATA
okta_py_ma-0.0.2.dist-info/WHEEL
okta_py_ma-0.0.2.dist-info/top_level.txt
okta_py_ma-0.0.2.dist-info/RECORD
