Metadata-Version: 2.1
Name: okta-py-ma
Version: 0.0.2
Summary: Wrappers for the Okta API for use with multithreaded scripts
Author-email: Michael Allen <michaelallenprofessional@gmail.com>
License: MIT License        
Project-URL: Homepage, https://github.com/michaelallenprofessional/OktaPythonMA
Project-URL: Bug Tracker, https://github.com/michaelallenprofessional/OktaPythonMA/issues
Classifier: Programming Language :: Python :: 3
Classifier: License :: OSI Approved :: MIT License
Classifier: Operating System :: OS Independent
Requires-Python: >=3.9
License-File: LICENSE
